odoo/addons/ssi_general_audit_worksheet_engagement_letter_checklist/README.rst
odoo/addons/ssi_general_audit_worksheet_engagement_letter_checklist/__init__.py
odoo/addons/ssi_general_audit_worksheet_engagement_letter_checklist/__manifest__.py
odoo/addons/ssi_general_audit_worksheet_engagement_letter_checklist/data/general_audit_worksheet_type_data.xml
odoo/addons/ssi_general_audit_worksheet_engagement_letter_checklist/data/approval_template/general_audit_ws_d8aaebc.xml
odoo/addons/ssi_general_audit_worksheet_engagement_letter_checklist/data/ir_sequence/general_audit_ws_d8aaebc.xml
odoo/addons/ssi_general_audit_worksheet_engagement_letter_checklist/data/policy_template/general_audit_ws_d8aaebc.xml
odoo/addons/ssi_general_audit_worksheet_engagement_letter_checklist/data/sequence_template/general_audit_ws_d8aaebc.xml
odoo/addons/ssi_general_audit_worksheet_engagement_letter_checklist/models/__init__.py
odoo/addons/ssi_general_audit_worksheet_engagement_letter_checklist/models/general_audit_engagement_checklist_item.py
odoo/addons/ssi_general_audit_worksheet_engagement_letter_checklist/models/general_audit_ws_d8aaebc.py
odoo/addons/ssi_general_audit_worksheet_engagement_letter_checklist/models/general_audit_ws_d8aaebc_checklist.py
odoo/addons/ssi_general_audit_worksheet_engagement_letter_checklist/security/ir.model.access.csv
odoo/addons/ssi_general_audit_worksheet_engagement_letter_checklist/security/ir_module_category_data.xml
odoo/addons/ssi_general_audit_worksheet_engagement_letter_checklist/security/res_group_data.xml
odoo/addons/ssi_general_audit_worksheet_engagement_letter_checklist/security/ir_model_access/general_audit_ws_d8aaebc.xml
odoo/addons/ssi_general_audit_worksheet_engagement_letter_checklist/security/ir_rule/general_audit_ws_d8aaebc.xml
odoo/addons/ssi_general_audit_worksheet_engagement_letter_checklist/security/res_group/general_audit_ws_d8aaebc.xml
odoo/addons/ssi_general_audit_worksheet_engagement_letter_checklist/static/description/icon.png
odoo14_addon_ssi_general_audit_worksheet_engagement_letter_checklist-14.0.1.0.0.dist-info/METADATA
odoo14_addon_ssi_general_audit_worksheet_engagement_letter_checklist-14.0.1.0.0.dist-info/WHEEL
odoo14_addon_ssi_general_audit_worksheet_engagement_letter_checklist-14.0.1.0.0.dist-info/top_level.txt
odoo14_addon_ssi_general_audit_worksheet_engagement_letter_checklist-14.0.1.0.0.dist-info/RECORD
